bk_precision_1900/__init__.py
bk_precision_1900/bk1902b.py
bk_precision_1900/bk_demo.py
bk_precision_1900-1.1.1.dist-info/licenses/LICENSE
bk_precision_1900-1.1.1.dist-info/METADATA
bk_precision_1900-1.1.1.dist-info/WHEEL
bk_precision_1900-1.1.1.dist-info/entry_points.txt
bk_precision_1900-1.1.1.dist-info/top_level.txt
bk_precision_1900-1.1.1.dist-info/RECORD
