Metadata-Version: 2.4
Name: bk-precision-1900
Version: 1.1.1
Summary: Control the BK Precision 1900 series power supplies
Author-email: Carlos Asmat <casmat@dephy.com>
License: MIT
Project-URL: Homepage, https://github.com/DephyInc/bk-precision-1900
Project-URL: Repository, https://github.com/DephyInc/bk-precision-1900
Project-URL: Issues, https://github.com/DephyInc/bk-precision-1900/issues
Keywords: B&K,BK Precision,hardware,serial,power-supply
Classifier: Programming Language :: Python :: 3
Classifier: Programming Language :: Python :: 3.12
Classifier: License :: OSI Approved :: MIT License
Classifier: Operating System :: OS Independent
Classifier: Topic :: System :: Hardware
Classifier: Topic :: Scientific/Engineering
Classifier: Typing :: Typed
Requires-Python: >=3.12
License-File: LICENSE
Requires-Dist: pyserial>=3.5
Dynamic: license-file
